pdf_requirement_extractor-2.0.0.dist-info/licenses/LICENSE
pdf_requirements_extractor/__init__.py
pdf_requirements_extractor/cli.py
pdf_requirements_extractor/extractor.py
pdf_requirements_extractor/gpt_parser.py
pdf_requirements_extractor/utils.py
pdf_requirement_extractor-2.0.0.dist-info/METADATA
pdf_requirement_extractor-2.0.0.dist-info/WHEEL
pdf_requirement_extractor-2.0.0.dist-info/entry_points.txt
pdf_requirement_extractor-2.0.0.dist-info/top_level.txt
pdf_requirement_extractor-2.0.0.dist-info/RECORD
