Metadata-Version: 2.4
Name: pdf-requirement-extractor
Version: 2.0.0
Summary: Extract structured brand requirements from PDF documents
Home-page: https://pypi.org/project/pdf-requirement-extractor/
Author: S M Asiful Islam Saky
Author-email: S M Asiful Islam Saky <saky.aiu22@gmail.com>
License-Expression: MIT
Project-URL: Homepage, https://pypi.org/project/pdf-requirement-extractor/
Project-URL: Documentation, https://pypi.org/project/pdf-requirement-extractor/
Project-URL: Source Code, https://pypi.org/project/pdf-requirement-extractor/
Project-URL: Download, https://pypi.org/project/pdf-requirement-extractor/#files
Keywords: pdf,extraction,brand,requirements,guidelines,parsing,text-processing,document-analysis,openai,gpt
Classifier: Development Status :: 5 - Production/Stable
Classifier: Intended Audience :: Developers
Classifier: Intended Audience :: Information Technology
Classifier: Operating System :: OS Independent
Classifier: Programming Language :: Python :: 3
Classifier: Programming Language :: Python :: 3.9
Classifier: Programming Language :: Python :: 3.10
Classifier: Programming Language :: Python :: 3.11
Classifier: Programming Language :: Python :: 3.12
Classifier: Topic :: Software Development :: Libraries :: Python Modules
Classifier: Topic :: Text Processing :: General
Classifier: Topic :: Office/Business
Classifier: Topic :: Multimedia :: Graphics
Requires-Python: >=3.9
License-File: LICENSE
Requires-Dist: pymupdf>=1.23.0
Requires-Dist: regex>=2023.10.3
Requires-Dist: typing-extensions>=4.5.0
Provides-Extra: gpt
Requires-Dist: openai>=1.3.0; extra == "gpt"
Provides-Extra: ocr
Requires-Dist: pytesseract>=0.3.10; extra == "ocr"
Requires-Dist: Pillow>=10.0.0; extra == "ocr"
Provides-Extra: dev
Requires-Dist: pytest>=7.0.0; extra == "dev"
Requires-Dist: pytest-cov>=4.0.0; extra == "dev"
Requires-Dist: black>=23.0.0; extra == "dev"
Requires-Dist: flake8>=6.0.0; extra == "dev"
Requires-Dist: mypy>=1.0.0; extra == "dev"
Requires-Dist: pre-commit>=3.0.0; extra == "dev"
Requires-Dist: isort>=5.12.0; extra == "dev"
Requires-Dist: bandit>=1.7.0; extra == "dev"
Requires-Dist: safety>=2.0.0; extra == "dev"
Requires-Dist: twine>=4.0.0; extra == "dev"
Requires-Dist: build>=0.10.0; extra == "dev"
Provides-Extra: all
Requires-Dist: openai>=1.3.0; extra == "all"
Requires-Dist: pytesseract>=0.3.10; extra == "all"
Requires-Dist: Pillow>=10.0.0; extra == "all"
Dynamic: author
Dynamic: home-page
Dynamic: license-file
Dynamic: requires-python
